{"resolvedId":"/home/edge/dev/js/private-cloud/node_modules/solid-start/entry-client/index.tsx?v=2963516b","transforms":[{"name":"__load__","result":"export { default as mount } from \"./mount\";\nexport { default as StartClient } from \"./StartClient\";\n","start":1675681830719,"end":1675681830719},{"name":"solid","result":"export { default as mount } from \"./mount\";\nexport { default as StartClient } from \"./StartClient\";","start":1675681830719,"end":1675681830722,"order":"pre"},{"name":"vite:import-analysis","result":"export { default as mount } from \"/node_modules/solid-start/entry-client/mount.tsx?v=2963516b\";\nexport { default as StartClient } from \"/node_modules/solid-start/entry-client/StartClient.tsx?t=1675681830435&v=2963516b\";","start":1675681830722,"end":1675681830723,"order":"normal"}]}
